educelab/imgproc/__init__.py
educelab/imgproc/adjust.py
educelab/imgproc/conversion.py
educelab/imgproc/correction.py
educelab/imgproc/enhance.py
educelab/imgproc/exiftool.py
educelab/imgproc/filters.py
educelab/imgproc/pca.py
educelab/imgproc/pipeline.py
educelab/imgproc/properties.py
educelab/imgproc/roi.py
educelab/imgproc/editor/__init__.py
educelab/imgproc/editor/cards.py
educelab/imgproc/editor/main.py
educelab/imgproc/editor/main_window.py
educelab/imgproc/editor/util.py
educelab/imgproc/editor/widgets.py
educelab/imgproc/editor/workers.py
educelab_imgproc-0.6.0.dist-info/LICENSE
educelab_imgproc-0.6.0.dist-info/METADATA
educelab_imgproc-0.6.0.dist-info/NOTICE
educelab_imgproc-0.6.0.dist-info/WHEEL
educelab_imgproc-0.6.0.dist-info/entry_points.txt
educelab_imgproc-0.6.0.dist-info/top_level.txt
educelab_imgproc-0.6.0.dist-info/RECORD
