Metadata-Version: 2.1
Name: educelab-imgproc
Version: 0.6.0
Summary: EduceLab image processing module
Home-page: https://educelab.gitlab.io/educelab-imgproc/
Download-URL: https://gitlab.com/educelab/educelab-imgproc
Author: Seth Parker
Author-email: c.seth.parker@uky.edu
Classifier: Programming Language :: Python :: 3
Classifier: Programming Language :: Python :: 3.9
Classifier: Programming Language :: Python :: 3.10
Classifier: Programming Language :: Python :: 3.11
Classifier: Programming Language :: Python :: 3.12
Classifier: Operating System :: OS Independent
Classifier: License :: OSI Approved :: GNU Affero General Public License v3
Requires-Python: >=3.9
License-File: LICENSE
License-File: NOTICE
Requires-Dist: educelab-cmdparse >=0.2
Requires-Dist: numpy
Requires-Dist: scipy
Requires-Dist: scikit-image
Requires-Dist: scikit-learn
Provides-Extra: docs
Requires-Dist: sphinx ; extra == 'docs'
Requires-Dist: sphinx-rtd-theme ; extra == 'docs'
Provides-Extra: gui
Requires-Dist: PySide6 ; extra == 'gui'
Requires-Dist: PySide6-QtAds ; extra == 'gui'
Requires-Dist: imageio ; extra == 'gui'
Requires-Dist: imagecodecs ; extra == 'gui'
